krishna_qlearn-0.1.0.dist-info/licenses/LICENSE
qlearn/__init__.py
qlearn/qlearn.py
tests/test_qlearn.py
krishna_qlearn-0.1.0.dist-info/METADATA
krishna_qlearn-0.1.0.dist-info/WHEEL
krishna_qlearn-0.1.0.dist-info/top_level.txt
krishna_qlearn-0.1.0.dist-info/RECORD
