Metadata-Version: 2.4
Name: krishna-qlearn
Version: 0.1.0
Summary: Tiny tabular Q-learning utilities for discrete environments
Author: Krishna Bolia
Author-email: Krishna Bolia <krishnajain508@gmail.com>
License: MIT
Classifier: Programming Language :: Python :: 3
Classifier: License :: OSI Approved :: MIT License
Classifier: Operating System :: OS Independent
Requires-Python: >=3.8
License-File: LICENSE
Requires-Dist: numpy
Dynamic: license-file
